odoo/addons/barcodes_generator_package/README.rst
odoo/addons/barcodes_generator_package/__init__.py
odoo/addons/barcodes_generator_package/__manifest__.py
odoo/addons/barcodes_generator_package/demo/barcode_rule.xml
odoo/addons/barcodes_generator_package/demo/function.xml
odoo/addons/barcodes_generator_package/demo/ir_sequence.xml
odoo/addons/barcodes_generator_package/demo/product_packaging.xml
odoo/addons/barcodes_generator_package/i18n/barcodes_generator_package.pot
odoo/addons/barcodes_generator_package/i18n/es.po
odoo/addons/barcodes_generator_package/i18n/es_ES.po
odoo/addons/barcodes_generator_package/i18n/fr.po
odoo/addons/barcodes_generator_package/i18n/hr.po
odoo/addons/barcodes_generator_package/i18n/nl_NL.po
odoo/addons/barcodes_generator_package/models/__init__.py
odoo/addons/barcodes_generator_package/models/barcode_rule.py
odoo/addons/barcodes_generator_package/models/product_packaging.py
odoo/addons/barcodes_generator_package/readme/CONFIGURE.rst
odoo/addons/barcodes_generator_package/readme/CONTRIBUTORS.rst
odoo/addons/barcodes_generator_package/readme/CREDITS.rst
odoo/addons/barcodes_generator_package/readme/DESCRIPTION.rst
odoo/addons/barcodes_generator_package/readme/USAGE.rst
odoo/addons/barcodes_generator_package/static/description/icon.png
odoo/addons/barcodes_generator_package/static/description/index.html
odoo/addons/barcodes_generator_package/static/description/product_packaging_sequence_generation.png
odoo/addons/barcodes_generator_package/tests/__init__.py
odoo/addons/barcodes_generator_package/tests/test_barcode_generator.py
odoo/addons/barcodes_generator_package/views/product_packaging.xml
odoo14_addon_barcodes_generator_package-14.0.1.0.1.dist-info/METADATA
odoo14_addon_barcodes_generator_package-14.0.1.0.1.dist-info/WHEEL
odoo14_addon_barcodes_generator_package-14.0.1.0.1.dist-info/top_level.txt
odoo14_addon_barcodes_generator_package-14.0.1.0.1.dist-info/RECORD
